cto_cli/__init__.py
cto_cli/ecs/api/__init__.py
cto_cli/ecs/api/connector.py
cto_cli/ecs/commands/__init__.py
cto_cli/ecs/commands/config.py
cto_cli/ecs/commands/users.py
cto_cli/ecs/local/__init__.py
cto_cli/ecs/local/commands.py
cto_cli/ecs/local/files.py
cto_cli/ecs/local/operations.py
cto_cli/ecs/local/settings.py
cto_cli/ecs/local/validators.py
cto_cli/ecs/main.py
cto_cli/main.py
cto_cli/utils/errors.py
cto_cli-0.4.1.dist-info/LICENSE
cto_cli-0.4.1.dist-info/METADATA
cto_cli-0.4.1.dist-info/WHEEL
cto_cli-0.4.1.dist-info/entry_points.txt
cto_cli-0.4.1.dist-info/RECORD
